mbls/__init__.py
mbls/py.typed
mbls/solver_status.py
mbls/time_stamped_recorder.py
mbls/cpsat/__init__.py
mbls/cpsat/cp_model_with_fixed_interval.py
mbls/cpsat/cp_model_with_flexible_interval.py
mbls/cpsat/cp_model_with_optional_fixed_interval.py
mbls/cpsat/cp_subroutine_controller.py
mbls/cpsat/custom_cp_model.py
mbls/cpsat/obj_value_bound_store.py
mbls/cpsat/solution_progress_logger.py
mbls/cpsat/solver_report.py
mbls/cpsat/status.py
mbls/cpsat/callbacks/__init__.py
mbls/cpsat/callbacks/base_solution_callback.py
mbls/cpsat/callbacks/by_call_recorder.py
mbls/cpsat/callbacks/by_callback_recorder.py
mbls/cpsat/callbacks/improv_timeout_callback.py
mbls/cpsat/callbacks/improv_timeout_value_recorder.py
mbls/cpsat/callbacks/objective_bound_recorder.py
mbls/cpsat/callbacks/objective_value_recorder.py
mbls/painter/__init__.py
mbls/painter/obj_value_bound_plotter.py
mbls/painter/time_series_plotter.py
mbls-0.0.13.dist-info/METADATA
mbls-0.0.13.dist-info/WHEEL
mbls-0.0.13.dist-info/RECORD
