Metadata-Version: 2.4
Name: mbls
Version: 0.0.13
Summary: Model-Based Local Search algorithm designer built on Routix
Project-URL: Repository, https://github.com/MSOLab/mbls.git
Author-email: JuneTech <junetech0@gmail.com>
License-Expression: MIT
Requires-Python: ==3.11.*
Requires-Dist: matplotlib>=3.10.3
Requires-Dist: routix==0.0.13
